{
  "annotations": {
    "list": [
      {
        "builtIn": 1,
        "datasource": {
          "type": "datasource",
          "uid": "grafana"
        },
        "enable": true,
        "hide": true,
        "iconColor": "rgba(0, 211, 255, 1)",
        "name": "Annotations & Alerts",
        "type": "dashboard"
      }
    ]
  },
  "description": "Monitor Windows systems via Telegraf and InfluxDB",
  "editable": true,
  "fiscalYearStartMonth": 0,
  "gnetId": 10411,
  "graphTooltip": 0,
  "id": 4,
  "links": [],
  "liveNow": false,
  "panels": [
    {
      "collapsed": true,
      "gridPos": {
        "h": 1,
        "w": 24,
        "x": 0,
        "y": 0
      },
      "id": 31,
      "panels": [
        {
          "datasource": {
            "type": "influxdb",
            "uid": "cc84647a-bef0-430a-a594-019ff6a3715b"
          },
          "fieldConfig": {
            "defaults": {
              "color": {
                "mode": "continuous-GrYlRd"
              },
              "custom": {
                "axisCenteredZero": false,
                "axisColorMode": "text",
                "axisLabel": "",
                "axisPlacement": "auto",
                "barAlignment": 0,
                "drawStyle": "line",
                "fillOpacity": 20,
                "gradientMode": "scheme",
                "hideFrom": {
                  "legend": false,
                  "tooltip": false,
                  "viz": false
                },
                "lineInterpolation": "smooth",
                "lineWidth": 3,
                "pointSize": 5,
                "scaleDistribution": {
                  "type": "linear"
                },
                "showPoints": "auto",
                "spanNulls": false,
                "stacking": {
                  "group": "A",
                  "mode": "none"
                },
                "thresholdsStyle": {
                  "mode": "off"
                }
              },
              "mappings": [],
              "thresholds": {
                "mode": "absolute",
                "steps": [
                  {
                    "color": "green",
                    "value": null
                  },
                  {
                    "color": "red",
                    "value": 80
                  }
                ]
              }
            },
            "overrides": []
          },
          "gridPos": {
            "h": 8,
            "w": 12,
            "x": 0,
            "y": 1
          },
          "id": 32,
          "options": {
            "legend": {
              "calcs": [
                "lastNotNull"
              ],
              "displayMode": "list",
              "placement": "bottom",
              "showLegend": true
            },
            "tooltip": {
              "mode": "single",
              "sort": "none"
            }
          },
          "targets": [
            {
              "datasource": {
                "type": "influxdb",
                "uid": "cc84647a-bef0-430a-a594-019ff6a3715b"
              },
              "groupBy": [
                {
                  "params": [
                    "$__interval"
                  ],
                  "type": "time"
                },
                {
                  "params": [
                    "host::tag"
                  ],
                  "type": "tag"
                }
              ],
              "measurement": "win_swap",
              "orderByTime": "ASC",
              "policy": "default",
              "refId": "A",
              "resultFormat": "time_series",
              "select": [
                [
                  {
                    "params": [
                      "Percent_Usage"
                    ],
                    "type": "field"
                  },
                  {
                    "params": [],
                    "type": "mean"
                  }
                ]
              ],
              "tags": [
                {
                  "key": "host",
                  "operator": "=~",
                  "value": "/^$Host$/"
                }
              ]
            }
          ],
          "title": "$Host - SWAP",
          "type": "timeseries"
        }
      ],
      "repeat": "Host",
      "repeatDirection": "h",
      "title": "$Host-SWAP",
      "type": "row"
    },
    {
      "collapsed": true,
      "datasource": {
        "type": "influxdb",
        "uid": "cc84647a-bef0-430a-a594-019ff6a3715b"
      },
      "gridPos": {
        "h": 1,
        "w": 24,
        "x": 0,
        "y": 1
      },
      "id": 12,
      "panels": [
        {
          "aliasColors": {},
          "bars": false,
          "dashLength": 10,
          "dashes": false,
          "datasource": {
            "type": "influxdb",
            "uid": "cc84647a-bef0-430a-a594-019ff6a3715b"
          },
          "editable": true,
          "error": false,
          "fill": 1,
          "fillGradient": 0,
          "grid": {},
          "gridPos": {
            "h": 7,
            "w": 12,
            "x": 0,
            "y": 10
          },
          "height": "350",
          "hiddenSeries": false,
          "id": 4,
          "interval": "",
          "legend": {
            "alignAsTable": false,
            "avg": true,
            "current": false,
            "hideZero": true,
            "max": false,
            "min": false,
            "rightSide": false,
            "show": true,
            "sort": "current",
            "sortDesc": true,
            "total": false,
            "values": true
          },
          "lines": true,
          "linewidth": 1,
          "links": [],
          "nullPointMode": "connected",
          "options": {
            "alertThreshold": true
          },
          "percentage": false,
          "pluginVersion": "10.0.3",
          "pointradius": 5,
          "points": false,
          "renderer": "flot",
          "seriesOverrides": [],
          "spaceLength": 10,
          "stack": false,
          "steppedLine": false,
          "targets": [
            {
              "alias": "$tag_host: $col",
              "datasource": {
                "type": "influxdb",
                "uid": "cc84647a-bef0-430a-a594-019ff6a3715b"
              },
              "dsType": "influxdb",
              "function": "mean",
              "groupBy": [
                {
                  "interval": "auto",
                  "params": [
                    "$__interval"
                  ],
                  "type": "time"
                },
                {
                  "key": "host",
                  "params": [
                    "host"
                  ],
                  "type": "tag"
                }
              ],
              "hide": false,
              "measurement": "win_cpu",
              "orderByTime": "ASC",
              "policy": "default",
              "query": "SELECT mean(\"%_Interrupt_Time\") as \"% Interrupt Time\", mean(\"%_Privileged_Time\") as \"% Privileged Time\", mean(\"%_Processor_Time\") as \"% Processor Time\", mean(\"%_User_Time\") as \"% User Time\" FROM \"win_cpu\" WHERE \"host\" =~ /$server$/ AND $timeFilter GROUP BY time($interval), *",
              "rawQuery": false,
              "refId": "B",
              "resultFormat": "time_series",
              "select": [
                [
                  {
                    "params": [
                      "Percent_Interrupt_Time"
                    ],
                    "type": "field"
                  },
                  {
                    "params": [],
                    "type": "mean"
                  },
                  {
                    "params": [
                      "% Interrupt"
                    ],
                    "type": "alias"
                  }
                ],
                [
                  {
                    "params": [
                      "Percent_Privileged_Time"
                    ],
                    "type": "field"
                  },
                  {
                    "params": [],
                    "type": "mean"
                  },
                  {
                    "params": [
                      "% Privileged"
                    ],
                    "type": "alias"
                  }
                ],
                [
                  {
                    "params": [
                      "Percent_Processor_Time"
                    ],
                    "type": "field"
                  },
                  {
                    "params": [],
                    "type": "mean"
                  },
                  {
                    "params": [
                      "% Processor"
                    ],
                    "type": "alias"
                  }
                ],
                [
                  {
                    "params": [
                      "Percent_User_Time"
                    ],
                    "type": "field"
                  },
                  {
                    "params": [],
                    "type": "mean"
                  },
                  {
                    "params": [
                      "% User"
                    ],
                    "type": "alias"
                  }
                ],
                [
                  {
                    "params": [
                      "Percent_Idle_Time"
                    ],
                    "type": "field"
                  },
                  {
                    "params": [],
                    "type": "mean"
                  },
                  {
                    "params": [
                      "% Idle"
                    ],
                    "type": "alias"
                  }
                ],
                [
                  {
                    "params": [
                      "Percent_DPC_Time"
                    ],
                    "type": "field"
                  },
                  {
                    "params": [],
                    "type": "mean"
                  },
                  {
                    "params": [
                      "% DPC"
                    ],
                    "type": "alias"
                  }
                ]
              ],
              "tags": [
                {
                  "key": "host",
                  "operator": "=~",
                  "value": "/^$Host$/"
                }
              ]
            }
          ],
          "thresholds": [],
          "timeRegions": [],
          "title": "$Host - CPU Usage",
          "tooltip": {
            "msResolution": false,
            "shared": true,
            "sort": 0,
            "value_type": "cumulative"
          },
          "type": "graph",
          "xaxis": {
            "mode": "time",
            "show": true,
            "values": []
          },
          "yaxes": [
            {
              "format": "percent",
              "logBase": 1,
              "max": 100,
              "min": 0,
              "show": true
            },
            {
              "format": "short",
              "logBase": 1,
              "show": true
            }
          ],
          "yaxis": {
            "align": false
          }
        }
      ],
      "targets": [
        {
          "datasource": {
            "type": "influxdb",
            "uid": "cc84647a-bef0-430a-a594-019ff6a3715b"
          },
          "refId": "A"
        }
      ],
      "title": "$Host - CPU",
      "type": "row"
    },
    {
      "collapsed": true,
      "datasource": {
        "type": "influxdb",
        "uid": "cc84647a-bef0-430a-a594-019ff6a3715b"
      },
      "gridPos": {
        "h": 1,
        "w": 24,
        "x": 0,
        "y": 2
      },
      "id": 16,
      "panels": [
        {
          "aliasColors": {},
          "bars": false,
          "dashLength": 10,
          "dashes": false,
          "datasource": {
            "type": "influxdb",
            "uid": "cc84647a-bef0-430a-a594-019ff6a3715b"
          },
          "editable": true,
          "error": false,
          "fill": 1,
          "fillGradient": 0,
          "grid": {},
          "gridPos": {
            "h": 7,
            "w": 12,
            "x": 0,
            "y": 11
          },
          "height": "400",
          "hiddenSeries": false,
          "id": 10,
          "interval": "",
          "legend": {
            "alignAsTable": false,
            "avg": false,
            "current": true,
            "max": true,
            "min": false,
            "show": true,
            "sort": "current",
            "sortDesc": true,
            "total": false,
            "values": true
          },
          "lines": true,
          "linewidth": 1,
          "links": [],
          "nullPointMode": "connected",
          "options": {
            "alertThreshold": true
          },
          "percentage": false,
          "pluginVersion": "10.0.3",
          "pointradius": 5,
          "points": false,
          "renderer": "flot",
          "seriesOverrides": [
            {
              "alias": "/mem_total/",
              "color": "#BF1B00",
              "fill": 0,
              "linewidth": 2
            }
          ],
          "spaceLength": 10,
          "stack": false,
          "steppedLine": false,
          "targets": [
            {
              "alias": "$tag_host: $col",
              "datasource": {
                "type": "influxdb",
                "uid": "cc84647a-bef0-430a-a594-019ff6a3715b"
              },
              "groupBy": [
                {
                  "params": [
                    "$__interval"
                  ],
                  "type": "time"
                },
                {
                  "params": [
                    "host"
                  ],
                  "type": "tag"
                },
                {
                  "params": [
                    "null"
                  ],
                  "type": "fill"
                }
              ],
              "measurement": "win_mem",
              "orderByTime": "DESC",
              "policy": "default",
              "refId": "B",
              "resultFormat": "time_series",
              "select": [
                [
                  {
                    "params": [
                      "Available_Bytes"
                    ],
                    "type": "field"
                  },
                  {
                    "params": [],
                    "type": "mean"
                  },
                  {
                    "params": [
                      "Available Bytes"
                    ],
                    "type": "alias"
                  }
                ],
                [
                  {
                    "params": [
                      "Pool_Nonpaged_Bytes"
                    ],
                    "type": "field"
                  },
                  {
                    "params": [],
                    "type": "mean"
                  },
                  {
                    "params": [
                      "Pool Nonpaged Bytes"
                    ],
                    "type": "alias"
                  }
                ],
                [
                  {
                    "params": [
                      "Pool_Paged_Bytes"
                    ],
                    "type": "field"
                  },
                  {
                    "params": [],
                    "type": "mean"
                  },
                  {
                    "params": [
                      "Pool paged Bytes"
                    ],
                    "type": "alias"
                  }
                ]
              ],
              "tags": [
                {
                  "key": "host",
                  "operator": "=~",
                  "value": "/^$Host$/"
                }
              ]
            }
          ],
          "thresholds": [],
          "timeRegions": [],
          "title": "$Host - Memory Usage",
          "tooltip": {
            "msResolution": false,
            "shared": true,
            "sort": 0,
            "value_type": "cumulative"
          },
          "type": "graph",
          "xaxis": {
            "mode": "time",
            "show": true,
            "values": []
          },
          "yaxes": [
            {
              "format": "decbytes",
              "logBase": 1,
              "min": 0,
              "show": true
            },
            {
              "format": "decbytes",
              "logBase": 1,
              "show": true
            }
          ],
          "yaxis": {
            "align": false
          }
        },
        {
          "aliasColors": {},
          "bars": false,
          "dashLength": 10,
          "dashes": false,
          "datasource": {
            "type": "influxdb",
            "uid": "cc84647a-bef0-430a-a594-019ff6a3715b"
          },
          "editable": true,
          "error": false,
          "fill": 1,
          "fillGradient": 0,
          "grid": {},
          "gridPos": {
            "h": 7,
            "w": 12,
            "x": 12,
            "y": 11
          },
          "height": "400",
          "hiddenSeries": false,
          "id": 24,
          "interval": "",
          "legend": {
            "alignAsTable": true,
            "avg": true,
            "current": true,
            "max": false,
            "min": false,
            "rightSide": true,
            "show": true,
            "sort": "current",
            "sortDesc": true,
            "total": false,
            "values": true
          },
          "lines": true,
          "linewidth": 1,
          "links": [],
          "nullPointMode": "connected",
          "options": {
            "alertThreshold": true
          },
          "percentage": false,
          "pluginVersion": "10.0.3",
          "pointradius": 5,
          "points": false,
          "renderer": "flot",
          "seriesOverrides": [
            {
              "alias": "/mem_total/",
              "color": "#BF1B00",
              "fill": 0,
              "linewidth": 2
            }
          ],
          "spaceLength": 10,
          "stack": false,
          "steppedLine": false,
          "targets": [
            {
              "alias": "$tag_host: $col",
              "datasource": {
                "type": "influxdb",
                "uid": "cc84647a-bef0-430a-a594-019ff6a3715b"
              },
              "groupBy": [
                {
                  "params": [
                    "$__interval"
                  ],
                  "type": "time"
                },
                {
                  "params": [
                    "host"
                  ],
                  "type": "tag"
                }
              ],
              "measurement": "win_mem",
              "orderByTime": "DESC",
              "policy": "default",
              "refId": "B",
              "resultFormat": "time_series",
              "select": [
                [
                  {
                    "params": [
                      "Cache_Faults_persec"
                    ],
                    "type": "field"
                  },
                  {
                    "params": [],
                    "type": "mean"
                  },
                  {
                    "params": [
                      "Cache Faults persec"
                    ],
                    "type": "alias"
                  }
                ],
                [
                  {
                    "params": [
                      "Demand_Zero_Faults_persec"
                    ],
                    "type": "field"
                  },
                  {
                    "params": [],
                    "type": "mean"
                  },
                  {
                    "params": [
                      "Demand Zero Faults persec"
                    ],
                    "type": "alias"
                  }
                ],
                [
                  {
                    "params": [
                      "Page_Faults_persec"
                    ],
                    "type": "field"
                  },
                  {
                    "params": [],
                    "type": "mean"
                  },
                  {
                    "params": [
                      "Page Faults persec"
                    ],
                    "type": "alias"
                  }
                ],
                [
                  {
                    "params": [
                      "Pages_persec"
                    ],
                    "type": "field"
                  },
                  {
                    "params": [],
                    "type": "mean"
                  },
                  {
                    "params": [
                      "Pages persec"
                    ],
                    "type": "alias"
                  }
                ],
                [
                  {
                    "params": [
                      "Transition_Faults_persec"
                    ],
                    "type": "field"
                  },
                  {
                    "params": [],
                    "type": "mean"
                  },
                  {
                    "params": [
                      "Transition Faults persec"
                    ],
                    "type": "alias"
                  }
                ]
              ],
              "tags": [
                {
                  "key": "host",
                  "operator": "=~",
                  "value": "/^$Host$/"
                }
              ]
            }
          ],
          "thresholds": [],
          "timeRegions": [],
          "title": "$Host - Memory Usage Rates",
          "tooltip": {
            "msResolution": false,
            "shared": true,
            "sort": 0,
            "value_type": "cumulative"
          },
          "type": "graph",
          "xaxis": {
            "mode": "time",
            "show": true,
            "values": []
          },
          "yaxes": [
            {
              "format": "none",
              "logBase": 1,
              "min": 0,
              "show": true
            },
            {
              "format": "short",
              "logBase": 1,
              "show": true
            }
          ],
          "yaxis": {
            "align": false
          }
        }
      ],
      "targets": [
        {
          "datasource": {
            "type": "influxdb",
            "uid": "cc84647a-bef0-430a-a594-019ff6a3715b"
          },
          "refId": "A"
        }
      ],
      "title": "$Host - Memory",
      "type": "row"
    },
    {
      "collapsed": true,
      "datasource": {
        "type": "influxdb",
        "uid": "cc84647a-bef0-430a-a594-019ff6a3715b"
      },
      "gridPos": {
        "h": 1,
        "w": 24,
        "x": 0,
        "y": 3
      },
      "id": 14,
      "panels": [
        {
          "aliasColors": {},
          "bars": false,
          "dashLength": 10,
          "dashes": false,
          "datasource": {
            "type": "influxdb",
            "uid": "cc84647a-bef0-430a-a594-019ff6a3715b"
          },
          "editable": true,
          "error": false,
          "fill": 1,
          "fillGradient": 0,
          "grid": {},
          "gridPos": {
            "h": 7,
            "w": 12,
            "x": 0,
            "y": 4
          },
          "hiddenSeries": false,
          "id": 2,
          "interval": "",
          "legend": {
            "alignAsTable": false,
            "avg": false,
            "current": true,
            "hideEmpty": false,
            "hideZero": false,
            "max": false,
            "min": false,
            "rightSide": false,
            "show": true,
            "sort": "current",
            "sortDesc": true,
            "total": false,
            "values": true
          },
          "lines": true,
          "linewidth": 1,
          "links": [],
          "maxPerRow": 2,
          "nullPointMode": "connected",
          "options": {
            "alertThreshold": true
          },
          "percentage": false,
          "pluginVersion": "10.0.3",
          "pointradius": 5,
          "points": false,
          "renderer": "flot",
          "seriesOverrides": [
            {
              "alias": "/total/",
              "color": "#BF1B00",
              "fill": 0,
              "linewidth": 2,
              "zindex": 3
            }
          ],
          "spaceLength": 10,
          "stack": false,
          "steppedLine": true,
          "targets": [
            {
              "alias": "$tag_host: $tag_instance - $col",
              "datasource": {
                "type": "influxdb",
                "uid": "cc84647a-bef0-430a-a594-019ff6a3715b"
              },
              "dsType": "influxdb",
              "function": "mean",
              "groupBy": [
                {
                  "interval": "auto",
                  "params": [
                    "$__interval"
                  ],
                  "type": "time"
                },
                {
                  "key": "host",
                  "params": [
                    "instance"
                  ],
                  "type": "tag"
                },
                {
                  "key": "path",
                  "params": [
                    "host"
                  ],
                  "type": "tag"
                }
              ],
              "measurement": "win_disk",
              "orderByTime": "ASC",
              "policy": "default",
              "query": "SELECT mean(\"Percent_Free_Space\") AS \"% Free Space\" FROM \"win_disk\" WHERE \"host\" =~ /$Host$/ AND $timeFilter GROUP BY time($__interval), \"host\", instance",
              "rawQuery": false,
              "refId": "B",
              "resultFormat": "time_series",
              "select": [
                [
                  {
                    "params": [
                      "Percent_Free_Space"
                    ],
                    "type": "field"
                  },
                  {
                    "params": [],
                    "type": "mean"
                  },
                  {
                    "params": [
                      "% Free"
                    ],
                    "type": "alias"
                  }
                ]
              ],
              "tags": [
                {
                  "key": "host",
                  "operator": "=~",
                  "value": "/^$Host$/"
                }
              ]
            }
          ],
          "thresholds": [],
          "timeRegions": [],
          "title": "$Host - Free Disk Space",
          "tooltip": {
            "msResolution": false,
            "shared": true,
            "sort": 0,
            "value_type": "cumulative"
          },
          "type": "graph",
          "xaxis": {
            "mode": "time",
            "show": true,
            "values": []
          },
          "yaxes": [
            {
              "format": "percent",
              "logBase": 1,
              "min": 0,
              "show": true
            },
            {
              "format": "short",
              "logBase": 1,
              "show": true
            }
          ],
          "yaxis": {
            "align": false
          }
        },
        {
          "aliasColors": {},
          "bars": false,
          "dashLength": 10,
          "dashes": false,
          "datasource": {
            "type": "influxdb",
            "uid": "cc84647a-bef0-430a-a594-019ff6a3715b"
          },
          "editable": true,
          "error": false,
          "fill": 1,
          "fillGradient": 0,
          "grid": {},
          "gridPos": {
            "h": 7,
            "w": 12,
            "x": 12,
            "y": 4
          },
          "hiddenSeries": false,
          "id": 8,
          "interval": "",
          "legend": {
            "alignAsTable": false,
            "avg": false,
            "current": true,
            "max": false,
            "min": false,
            "show": true,
            "sort": "current",
            "sortDesc": true,
            "total": false,
            "values": true
          },
          "lines": true,
          "linewidth": 1,
          "links": [],
          "maxPerRow": 2,
          "nullPointMode": "connected",
          "options": {
            "alertThreshold": true
          },
          "percentage": false,
          "pluginVersion": "10.0.3",
          "pointradius": 5,
          "points": false,
          "renderer": "flot",
          "seriesOverrides": [
            {
              "alias": "/total/",
              "color": "#BF1B00",
              "fill": 0,
              "linewidth": 2,
              "zindex": 3
            }
          ],
          "spaceLength": 10,
          "stack": false,
          "steppedLine": true,
          "targets": [
            {
              "alias": "$tag_host: $tag_instance - $col",
              "datasource": {
                "type": "influxdb",
                "uid": "cc84647a-bef0-430a-a594-019ff6a3715b"
              },
              "groupBy": [
                {
                  "params": [
                    "$__interval"
                  ],
                  "type": "time"
                },
                {
                  "params": [
                    "host"
                  ],
                  "type": "tag"
                },
                {
                  "params": [
                    "instance"
                  ],
                  "type": "tag"
                }
              ],
              "measurement": "win_disk",
              "orderByTime": "ASC",
              "policy": "default",
              "refId": "A",
              "resultFormat": "time_series",
              "select": [
                [
                  {
                    "params": [
                      "Current_Disk_Queue_Length"
                    ],
                    "type": "field"
                  },
                  {
                    "params": [],
                    "type": "mean"
                  },
                  {
                    "params": [
                      "Current Disk Queue Length"
                    ],
                    "type": "alias"
                  }
                ]
              ],
              "tags": [
                {
                  "key": "host",
                  "operator": "=~",
                  "value": "/^$Host$/"
                }
              ]
            }
          ],
          "thresholds": [],
          "timeRegions": [],
          "title": "$Host - Current Disk Queue Length",
          "tooltip": {
            "msResolution": false,
            "shared": true,
            "sort": 0,
            "value_type": "cumulative"
          },
          "type": "graph",
          "xaxis": {
            "mode": "time",
            "show": true,
            "values": []
          },
          "yaxes": [
            {
              "format": "none",
              "logBase": 1,
              "min": 0,
              "show": true
            },
            {
              "format": "short",
              "logBase": 1,
              "show": true
            }
          ],
          "yaxis": {
            "align": false
          }
        },
        {
          "aliasColors": {},
          "bars": false,
          "dashLength": 10,
          "dashes": false,
          "datasource": {
            "type": "influxdb",
            "uid": "cc84647a-bef0-430a-a594-019ff6a3715b"
          },
          "editable": true,
          "error": false,
          "fill": 1,
          "fillGradient": 0,
          "grid": {},
          "gridPos": {
            "h": 7,
            "w": 12,
            "x": 0,
            "y": 11
          },
          "hiddenSeries": false,
          "id": 6,
          "interval": "",
          "legend": {
            "alignAsTable": false,
            "avg": false,
            "current": true,
            "max": false,
            "min": false,
            "show": true,
            "sort": "current",
            "sortDesc": true,
            "total": false,
            "values": true
          },
          "lines": true,
          "linewidth": 1,
          "links": [],
          "maxPerRow": 2,
          "nullPointMode": "connected",
          "options": {
            "alertThreshold": true
          },
          "percentage": false,
          "pluginVersion": "10.0.3",
          "pointradius": 5,
          "points": false,
          "renderer": "flot",
          "seriesOverrides": [
            {
              "alias": "/total/",
              "color": "#BF1B00",
              "fill": 0,
              "linewidth": 2,
              "zindex": 3
            }
          ],
          "spaceLength": 10,
          "stack": false,
          "steppedLine": true,
          "targets": [
            {
              "alias": "$tag_host: $tag_instance - $col",
              "datasource": {
                "type": "influxdb",
                "uid": "cc84647a-bef0-430a-a594-019ff6a3715b"
              },
              "dsType": "influxdb",
              "function": "mean",
              "groupBy": [
                {
                  "interval": "auto",
                  "params": [
                    "$__interval"
                  ],
                  "type": "time"
                },
                {
                  "key": "host",
                  "params": [
                    "host"
                  ],
                  "type": "tag"
                },
                {
                  "key": "path",
                  "params": [
                    "instance"
                  ],
                  "type": "tag"
                }
              ],
              "measurement": "win_disk",
              "orderByTime": "ASC",
              "policy": "default",
              "query": "SELECT mean(\"%_Idle_Time\") AS \"% Idle Time\" FROM \"win_disk\" WHERE \"host\" =~ /$server$/ AND $timeFilter GROUP BY time($interval), \"host\", instance",
              "rawQuery": false,
              "refId": "B",
              "resultFormat": "time_series",
              "select": [
                [
                  {
                    "params": [
                      "Percent_Idle_Time"
                    ],
                    "type": "field"
                  },
                  {
                    "params": [],
                    "type": "mean"
                  },
                  {
                    "params": [
                      "% Idle"
                    ],
                    "type": "alias"
                  }
                ]
              ],
              "tags": [
                {
                  "key": "host",
                  "operator": "=~",
                  "value": "/^$Host$/"
                }
              ]
            }
          ],
          "thresholds": [],
          "timeRegions": [],
          "title": "$Host - Disk Idle Time",
          "tooltip": {
            "msResolution": false,
            "shared": true,
            "sort": 0,
            "value_type": "cumulative"
          },
          "type": "graph",
          "xaxis": {
            "mode": "time",
            "show": true,
            "values": []
          },
          "yaxes": [
            {
              "format": "percent",
              "logBase": 1,
              "min": 0,
              "show": true
            },
            {
              "format": "short",
              "logBase": 1,
              "show": true
            }
          ],
          "yaxis": {
            "align": false
          }
        }
      ],
      "targets": [
        {
          "datasource": {
            "type": "influxdb",
            "uid": "cc84647a-bef0-430a-a594-019ff6a3715b"
          },
          "refId": "A"
        }
      ],
      "title": "$Host - Disk Info",
      "type": "row"
    },
    {
      "collapsed": true,
      "datasource": {
        "type": "influxdb",
        "uid": "cc84647a-bef0-430a-a594-019ff6a3715b"
      },
      "gridPos": {
        "h": 1,
        "w": 24,
        "x": 0,
        "y": 4
      },
      "id": 18,
      "panels": [
        {
          "aliasColors": {},
          "bars": false,
          "dashLength": 10,
          "dashes": false,
          "datasource": {
            "type": "influxdb",
            "uid": "cc84647a-bef0-430a-a594-019ff6a3715b"
          },
          "editable": true,
          "error": false,
          "fill": 1,
          "fillGradient": 0,
          "grid": {},
          "gridPos": {
            "h": 7,
            "w": 24,
            "x": 0,
            "y": 13
          },
          "hiddenSeries": false,
          "id": 20,
          "interval": "",
          "legend": {
            "alignAsTable": true,
            "avg": true,
            "current": true,
            "max": false,
            "min": false,
            "rightSide": true,
            "show": true,
            "sort": "current",
            "sortDesc": true,
            "total": false,
            "values": true
          },
          "lines": true,
          "linewidth": 1,
          "links": [],
          "maxPerRow": 2,
          "nullPointMode": "connected",
          "options": {
            "alertThreshold": true
          },
          "percentage": false,
          "pluginVersion": "10.0.3",
          "pointradius": 5,
          "points": false,
          "renderer": "flot",
          "seriesOverrides": [
            {
              "alias": "/total/",
              "color": "#BF1B00",
              "fill": 0,
              "linewidth": 2,
              "zindex": 3
            }
          ],
          "spaceLength": 10,
          "stack": false,
          "steppedLine": true,
          "targets": [
            {
              "alias": "$tag_host:  $tag_instance - $col",
              "datasource": {
                "type": "influxdb",
                "uid": "cc84647a-bef0-430a-a594-019ff6a3715b"
              },
              "groupBy": [
                {
                  "params": [
                    "$__interval"
                  ],
                  "type": "time"
                },
                {
                  "params": [
                    "host"
                  ],
                  "type": "tag"
                },
                {
                  "params": [
                    "instance"
                  ],
                  "type": "tag"
                }
              ],
              "measurement": "win_net",
              "orderByTime": "ASC",
              "policy": "default",
              "refId": "A",
              "resultFormat": "time_series",
              "select": [
                [
                  {
                    "params": [
                      "Bytes_Received_persec"
                    ],
                    "type": "field"
                  },
                  {
                    "params": [],
                    "type": "mean"
                  },
                  {
                    "params": [
                      "Bytes Received persec"
                    ],
                    "type": "alias"
                  }
                ],
                [
                  {
                    "params": [
                      "Bytes_Sent_persec"
                    ],
                    "type": "field"
                  },
                  {
                    "params": [],
                    "type": "mean"
                  },
                  {
                    "params": [
                      "Bytes Sent persec"
                    ],
                    "type": "alias"
                  }
                ]
              ],
              "tags": [
                {
                  "key": "host",
                  "operator": "=~",
                  "value": "/^$Host$/"
                }
              ]
            }
          ],
          "thresholds": [],
          "timeRegions": [],
          "title": "$Host - Network Usage",
          "tooltip": {
            "msResolution": false,
            "shared": true,
            "sort": 0,
            "value_type": "cumulative"
          },
          "type": "graph",
          "xaxis": {
            "mode": "time",
            "show": true,
            "values": []
          },
          "yaxes": [
            {
              "format": "Bps",
              "logBase": 1,
              "min": 0,
              "show": true
            },
            {
              "format": "short",
              "logBase": 1,
              "show": true
            }
          ],
          "yaxis": {
            "align": false
          }
        },
        {
          "aliasColors": {},
          "bars": false,
          "dashLength": 10,
          "dashes": false,
          "datasource": {
            "type": "influxdb",
            "uid": "cc84647a-bef0-430a-a594-019ff6a3715b"
          },
          "editable": true,
          "error": false,
          "fill": 1,
          "fillGradient": 0,
          "grid": {},
          "gridPos": {
            "h": 6,
            "w": 24,
            "x": 0,
            "y": 20
          },
          "hiddenSeries": false,
          "id": 22,
          "interval": "",
          "legend": {
            "alignAsTable": true,
            "avg": true,
            "current": true,
            "max": false,
            "min": false,
            "rightSide": true,
            "show": true,
            "sort": "current",
            "sortDesc": true,
            "total": false,
            "values": true
          },
          "lines": true,
          "linewidth": 1,
          "links": [],
          "maxPerRow": 2,
          "nullPointMode": "connected",
          "options": {
            "alertThreshold": true
          },
          "percentage": false,
          "pluginVersion": "10.0.3",
          "pointradius": 5,
          "points": false,
          "renderer": "flot",
          "seriesOverrides": [
            {
              "alias": "/total/",
              "color": "#BF1B00",
              "fill": 0,
              "linewidth": 2,
              "zindex": 3
            }
          ],
          "spaceLength": 10,
          "stack": false,
          "steppedLine": true,
          "targets": [
            {
              "alias": "$tag_host: $tag_instance - $col",
              "datasource": {
                "type": "influxdb",
                "uid": "cc84647a-bef0-430a-a594-019ff6a3715b"
              },
              "groupBy": [
                {
                  "params": [
                    "$__interval"
                  ],
                  "type": "time"
                },
                {
                  "params": [
                    "host"
                  ],
                  "type": "tag"
                },
                {
                  "params": [
                    "instance"
                  ],
                  "type": "tag"
                }
              ],
              "measurement": "win_net",
              "orderByTime": "ASC",
              "policy": "default",
              "refId": "A",
              "resultFormat": "time_series",
              "select": [
                [
                  {
                    "params": [
                      "Packets_Received_persec"
                    ],
                    "type": "field"
                  },
                  {
                    "params": [],
                    "type": "mean"
                  },
                  {
                    "params": [
                      "Packets Received persec"
                    ],
                    "type": "alias"
                  }
                ],
                [
                  {
                    "params": [
                      "Packets_Sent_persec"
                    ],
                    "type": "field"
                  },
                  {
                    "params": [],
                    "type": "mean"
                  },
                  {
                    "params": [
                      "Packets Sent persec"
                    ],
                    "type": "alias"
                  }
                ]
              ],
              "tags": [
                {
                  "key": "host",
                  "operator": "=~",
                  "value": "/^$Host$/"
                }
              ]
            }
          ],
          "thresholds": [],
          "timeRegions": [],
          "title": "$Host - Network Packets",
          "tooltip": {
            "msResolution": false,
            "shared": true,
            "sort": 0,
            "value_type": "cumulative"
          },
          "type": "graph",
          "xaxis": {
            "mode": "time",
            "show": true,
            "values": []
          },
          "yaxes": [
            {
              "format": "pps",
              "logBase": 1,
              "min": 0,
              "show": true
            },
            {
              "format": "short",
              "logBase": 1,
              "show": true
            }
          ],
          "yaxis": {
            "align": false
          }
        }
      ],
      "targets": [
        {
          "datasource": {
            "type": "influxdb",
            "uid": "cc84647a-bef0-430a-a594-019ff6a3715b"
          },
          "refId": "A"
        }
      ],
      "title": "$Host - Network",
      "type": "row"
    },
    {
      "collapsed": true,
      "datasource": {
        "type": "influxdb",
        "uid": "cc84647a-bef0-430a-a594-019ff6a3715b"
      },
      "gridPos": {
        "h": 1,
        "w": 24,
        "x": 0,
        "y": 5
      },
      "id": 26,
      "panels": [
        {
          "aliasColors": {},
          "bars": false,
          "dashLength": 10,
          "dashes": false,
          "datasource": {
            "type": "influxdb",
            "uid": "cc84647a-bef0-430a-a594-019ff6a3715b"
          },
          "editable": true,
          "error": false,
          "fill": 1,
          "fillGradient": 0,
          "grid": {},
          "gridPos": {
            "h": 7,
            "w": 12,
            "x": 0,
            "y": 14
          },
          "hiddenSeries": false,
          "id": 28,
          "interval": "",
          "legend": {
            "alignAsTable": true,
            "avg": true,
            "current": true,
            "max": true,
            "min": true,
            "show": true,
            "sort": "current",
            "sortDesc": true,
            "total": false,
            "values": true
          },
          "lines": true,
          "linewidth": 1,
          "links": [],
          "maxPerRow": 2,
          "nullPointMode": "connected",
          "options": {
            "alertThreshold": true
          },
          "percentage": false,
          "pluginVersion": "10.0.3",
          "pointradius": 5,
          "points": false,
          "renderer": "flot",
          "seriesOverrides": [
            {
              "alias": "/total/",
              "color": "#BF1B00",
              "fill": 0,
              "linewidth": 2,
              "zindex": 3
            }
          ],
          "spaceLength": 10,
          "stack": false,
          "steppedLine": true,
          "targets": [
            {
              "alias": "$tag_host: $tag_instance - $col",
              "datasource": {
                "type": "influxdb",
                "uid": "cc84647a-bef0-430a-a594-019ff6a3715b"
              },
              "groupBy": [
                {
                  "params": [
                    "$__interval"
                  ],
                  "type": "time"
                },
                {
                  "params": [
                    "host"
                  ],
                  "type": "tag"
                },
                {
                  "params": [
                    "instance"
                  ],
                  "type": "tag"
                }
              ],
              "measurement": "win_system",
              "orderByTime": "ASC",
              "policy": "default",
              "refId": "A",
              "resultFormat": "time_series",
              "select": [
                [
                  {
                    "params": [
                      "Context_Switches_persec"
                    ],
                    "type": "field"
                  },
                  {
                    "params": [],
                    "type": "mean"
                  },
                  {
                    "params": [
                      "Context Switches persec"
                    ],
                    "type": "alias"
                  }
                ]
              ],
              "tags": [
                {
                  "key": "host",
                  "operator": "=~",
                  "value": "/^$Host$/"
                }
              ]
            }
          ],
          "thresholds": [],
          "timeRegions": [],
          "title": "$Host - Context Switches",
          "tooltip": {
            "msResolution": false,
            "shared": true,
            "sort": 0,
            "value_type": "cumulative"
          },
          "type": "graph",
          "xaxis": {
            "mode": "time",
            "show": true,
            "values": []
          },
          "yaxes": [
            {
              "format": "none",
              "logBase": 1,
              "min": 0,
              "show": true
            },
            {
              "format": "short",
              "logBase": 1,
              "show": true
            }
          ],
          "yaxis": {
            "align": false
          }
        },
        {
          "aliasColors": {},
          "bars": false,
          "dashLength": 10,
          "dashes": false,
          "datasource": {
            "type": "influxdb",
            "uid": "cc84647a-bef0-430a-a594-019ff6a3715b"
          },
          "editable": true,
          "error": false,
          "fill": 1,
          "fillGradient": 0,
          "grid": {},
          "gridPos": {
            "h": 7,
            "w": 12,
            "x": 12,
            "y": 14
          },
          "hiddenSeries": false,
          "id": 30,
          "interval": "",
          "legend": {
            "alignAsTable": true,
            "avg": true,
            "current": true,
            "max": true,
            "min": true,
            "show": true,
            "sort": "current",
            "sortDesc": true,
            "total": false,
            "values": true
          },
          "lines": true,
          "linewidth": 1,
          "links": [],
          "maxPerRow": 2,
          "nullPointMode": "connected",
          "options": {
            "alertThreshold": true
          },
          "percentage": false,
          "pluginVersion": "10.0.3",
          "pointradius": 5,
          "points": false,
          "renderer": "flot",
          "seriesOverrides": [
            {
              "alias": "/total/",
              "color": "#BF1B00",
              "fill": 0,
              "linewidth": 2,
              "zindex": 3
            }
          ],
          "spaceLength": 10,
          "stack": false,
          "steppedLine": true,
          "targets": [
            {
              "alias": "$tag_host: mountpoint $tag_instance - $col",
              "datasource": {
                "type": "influxdb",
                "uid": "cc84647a-bef0-430a-a594-019ff6a3715b"
              },
              "dsType": "influxdb",
              "function": "mean",
              "groupBy": [
                {
                  "interval": "auto",
                  "params": [
                    "auto"
                  ],
                  "type": "time"
                },
                {
                  "key": "host",
                  "params": [
                    "tag"
                  ],
                  "type": "tag"
                },
                {
                  "key": "path",
                  "params": [
                    "tag"
                  ],
                  "type": "tag"
                }
              ],
              "measurement": "disk_total",
              "orderByTime": "ASC",
              "policy": "default",
              "query": "SELECT mean(\"System_Calls_persec\") AS \"System Calls persec\" FROM \"win_system\" WHERE \"host\" =~ /$server$/ AND $timeFilter GROUP BY time($interval), \"host\", instance",
              "rawQuery": true,
              "refId": "B",
              "resultFormat": "time_series",
              "select": [
                [
                  {
                    "params": [
                      "value"
                    ],
                    "type": "field"
                  },
                  {
                    "params": [],
                    "type": "mean"
                  }
                ]
              ],
              "tags": []
            },
            {
              "alias": "$tag_host: $tag_instance - $col",
              "datasource": {
                "type": "influxdb",
                "uid": "cc84647a-bef0-430a-a594-019ff6a3715b"
              },
              "groupBy": [
                {
                  "params": [
                    "$__interval"
                  ],
                  "type": "time"
                },
                {
                  "params": [
                    "host"
                  ],
                  "type": "tag"
                },
                {
                  "params": [
                    "instance"
                  ],
                  "type": "tag"
                }
              ],
              "measurement": "win_system",
              "orderByTime": "ASC",
              "policy": "default",
              "refId": "A",
              "resultFormat": "time_series",
              "select": [
                [
                  {
                    "params": [
                      "System_Calls_persec"
                    ],
                    "type": "field"
                  },
                  {
                    "params": [],
                    "type": "mean"
                  },
                  {
                    "params": [
                      "System Calls persec"
                    ],
                    "type": "alias"
                  }
                ]
              ],
              "tags": [
                {
                  "key": "host",
                  "operator": "=~",
                  "value": "/^$Host$/"
                }
              ]
            }
          ],
          "thresholds": [],
          "timeRegions": [],
          "title": "$Host - System Calls",
          "tooltip": {
            "msResolution": false,
            "shared": true,
            "sort": 0,
            "value_type": "cumulative"
          },
          "type": "graph",
          "xaxis": {
            "mode": "time",
            "show": true,
            "values": []
          },
          "yaxes": [
            {
              "format": "none",
              "logBase": 1,
              "min": 0,
              "show": true
            },
            {
              "format": "short",
              "logBase": 1,
              "show": true
            }
          ],
          "yaxis": {
            "align": false
          }
        }
      ],
      "targets": [
        {
          "datasource": {
            "type": "influxdb",
            "uid": "cc84647a-bef0-430a-a594-019ff6a3715b"
          },
          "refId": "A"
        }
      ],
      "title": "$Host - System",
      "type": "row"
    }
  ],
  "refresh": "1m",
  "schemaVersion": 38,
  "style": "dark",
  "tags": [
    "Windows",
    "Telegraf",
    "InfluxDB"
  ],
  "templating": {
    "list": [
      {
        "current": {
          "selected": false,
          "text": "DESKTOP-EG823RO",
          "value": "DESKTOP-EG823RO"
        },
        "datasource": {
          "type": "influxdb",
          "uid": "cc84647a-bef0-430a-a594-019ff6a3715b"
        },
        "definition": "SHOW TAG VALUES FROM win_system WITH KEY=host",
        "hide": 0,
        "includeAll": false,
        "label": "Host",
        "multi": false,
        "name": "Host",
        "options": [],
        "query": "SHOW TAG VALUES FROM win_system WITH KEY=host",
        "refresh": 1,
        "regex": "",
        "skipUrlSync": false,
        "sort": 0,
        "tagValuesQuery": "",
        "tagsQuery": "",
        "type": "query",
        "useTags": false
      }
    ]
  },
  "time": {
    "from": "now-1h",
    "to": "now"
  },
  "timepicker": {
    "refresh_intervals": [
      "5s",
      "10s",
      "30s",
      "1m",
      "5m",
      "15m",
      "30m",
      "1h",
      "2h",
      "1d"
    ],
    "time_options": [
      "5m",
      "15m",
      "1h",
      "6h",
      "12h",
      "24h",
      "2d",
      "7d",
      "30d"
    ]
  },
  "timezone": "",
  "title": "Windows System",
  "uid": "2YipkZ4ZzZ",
  "version": 3,
  "weekStart": ""
}